pitct/des_info.py
pitct/simulation.py
pitct/config.py
pitct/_version.py
pitct/util.py
pitct/dat_info.py
pitct/__init__.py
pitct/distance.py
pitct/des_check.py
pitct/libtct.cpython-314-darwin.so
pitct/libtct.c
pitct/name_converter.py
pitct/ext_des_info.py
pitct/automaton_display.py
pitct/tct_typing.py
pitct/tct_def.py
pitct/des.py
pitct-1.0.6.dist-info/RECORD
pitct-1.0.6.dist-info/WHEEL
pitct-1.0.6.dist-info/top_level.txt
pitct-1.0.6.dist-info/METADATA
pitct-1.0.6.dist-info/licenses/LICENSE
pitct-1.0.6.dist-info/licenses/libtct/LICENSE
