Metadata-Version: 2.4
Name: pitct
Version: 1.0.6
Summary: Python TCT Library
Author: Shoma Matsui, Masahiro Konishi
License-Expression: Apache-2.0 AND BSD-3-Clause
Project-URL: Homepage, https://omucai.github.io/PiTCT/
Project-URL: Documentation, https://omucai.github.io/PiTCT-docs/
Project-URL: Repository, https://github.com/OMUCAI/PiTCT.git
Keywords: pitct,control,discrete
Requires-Python: >=3.9
License-File: LICENSE
License-File: libtct/LICENSE
Requires-Dist: graphviz<0.23,>=0.20
Requires-Dist: u-msgpack-python<3.0.0,>=2.7.1
Provides-Extra: dev
Requires-Dist: flake8; extra == "dev"
Requires-Dist: black; extra == "dev"
Requires-Dist: build; extra == "dev"
Dynamic: license-file
